Workbook

Sheet Итог
A1: Себестоимость партии дверной фурнитуры — одна фура из Китая
A3: Статья | B3: USD | C3: сом | D3: % к FOB
A4: Товар (FOB Китай) | B4: =Заказ!I25 -> 135765 | C4: =B4*Параметры!$B$5 -> 11879438 | D4: =IF($B$4=0,0,B4/$B$4) -> 1
A5: Логистика (фура) | B5: =Заказ!N25 -> 9000 | C5: =B5*Параметры!$B$5 -> 787500 | D5: =IF($B$4=0,0,B5/$B$4) -> 0.066291018
A6: Страхование | B6: =Заказ!O25 -> 407.295 | C6: =B6*Параметры!$B$5 -> 35638.312 | D6: =IF($B$4=0,0,B6/$B$4) -> 0.003
A7: Ввозная пошлина | B7: =Заказ!Q25 -> 13349.09 | C7: =B7*Параметры!$B$5 -> 1168045.3 | D7: =IF($B$4=0,0,B7/$B$4) -> 0.09832497
A8: Таможенный сбор 0,4% | B8: =Заказ!R25 -> 573.48918 | C8: =B8*Параметры!$B$5 -> 50180.303 | D8: =IF($B$4=0,0,B8/$B$4) -> 0.0042241313
A9: НДС при импорте (в себестоимости, если включён) | B9: =Заказ!S25*Параметры!$B$13 -> 18806.566 | C9: =B9*Параметры!$B$5 -> 1645574.5 | D9: =IF($B$4=0,0,B9/$B$4) -> 0.13852293
A10: Брокер, СВХ, банк, агент, инспекция | B10: =Заказ!T25 -> 6830.6 | C10: =B10*Параметры!$B$5 -> 597677.5 | D10: =IF($B$4=0,0,B10/$B$4) -> 0.050311936
A11: Резерв на непредвиденные | B11: =Заказ!U25 -> 5541.9612 | C11: =B11*Параметры!$B$5 -> 484921.6 | D11: =IF($B$4=0,0,B11/$B$4) -> 0.04082025
A12: СЕБЕСТОИМОСТЬ ПАРТИИ | B12: =SUM(B4:B11) -> 190274 | C12: =B12*Параметры!$B$5 -> 16648975 | D12: =IF($B$4=0,0,B12/$B$4) -> 1.4014952
A13: Справочно: НДС к уплате на границе (деньги нужны в любом случае) | B13: =Заказ!S25 -> 18806.566 | C13: =B13*Параметры!$B$5 -> 1645574.5
A14: Нужно денег всего (товар + все расходы + НДС) | B14: =B12+Заказ!S25*(1-Параметры!$B$13) -> 190274 | C14: =B14*Параметры!$B$5 -> 16648975
A16: Показатели
A17: Вес партии, кг | B17: =Заказ!K25 -> 19462
A18: Загрузка фуры по весу | B18: =Заказ!K25/Параметры!$B$7 -> 0.9731
A19: Объём партии, м³ | B19: =Заказ!M25 -> 55.11
A20: Загрузка фуры по объёму | B20: =Заказ!M25/Параметры!$B$8 -> 0.64081395
A21: Единиц товара в заказе, шт/компл | B21: =Заказ!G25 -> 57300
A22: Логистика на 1 кг, $ | B22: =Заказ!N25/Заказ!K25 -> 0.46243963
A23: Таможенные платежи (пошлина+сбор+НДС), $ | B23: =Заказ!Q25+Заказ!R25+Заказ!S25 -> 32729.145
A24: Себестоимость к FOB (коэффициент) | B24: =B12/B4 -> 1.4014952
A25: Выручка при оптовой наценке, $ | B25: =B12*(1+Параметры!$B$20) -> 256869.9
A26: Валовая прибыль с партии, $ | B26: =B12*Параметры!$B$20 -> 66595.9
A29: По категориям | B29: FOB, $ | C29: Себестоимость, $ | D29: Вес, кг
A30: Ручки | B30: =SUMIF(Заказ!$B$5:$B$24,A30,Заказ!$I$5:$I$24) -> 38230 | C30: =SUMIF(Заказ!$B$5:$B$24,A30,Заказ!$V$5:$V$24) -> 53548.916 | D30: =SUMIF(Заказ!$B$5:$B$24,A30,Заказ!$K$5:$K$24) -> 4860
A31: Механизмы | B31: =SUMIF(Заказ!$B$5:$B$24,A31,Заказ!$I$5:$I$24) -> 21760 | C31: =SUMIF(Заказ!$B$5:$B$24,A31,Заказ!$V$5:$V$24) -> 30441.809 | D31: =SUMIF(Заказ!$B$5:$B$24,A31,Заказ!$K$5:$K$24) -> 2700
A32: Замки | B32: =SUMIF(Заказ!$B$5:$B$24,A32,Заказ!$I$5:$I$24) -> 22180 | C32: =SUMIF(Заказ!$B$5:$B$24,A32,Заказ!$V$5:$V$24) -> 31855.19 | D32: =SUMIF(Заказ!$B$5:$B$24,A32,Заказ!$K$5:$K$24) -> 3255
A33: Цилиндры | B33: =SUMIF(Заказ!$B$5:$B$24,A33,Заказ!$I$5:$I$24) -> 16840 | C33: =SUMIF(Заказ!$B$5:$B$24,A33,Заказ!$V$5:$V$24) -> 24099.65 | D33: =SUMIF(Заказ!$B$5:$B$24,A33,Заказ!$K$5:$K$24) -> 1276
A34: Фиксаторы | B34: =SUMIF(Заказ!$B$5:$B$24,A34,Заказ!$I$5:$I$24) -> 3640 | C34: =SUMIF(Заказ!$B$5:$B$24,A34,Заказ!$V$5:$V$24) -> 5057.3766 | D34: =SUMIF(Заказ!$B$5:$B$24,A34,Заказ!$K$5:$K$24) -> 390
A35: Петли | B35: =SUMIF(Заказ!$B$5:$B$24,A35,Заказ!$I$5:$I$24) -> 21470 | C35: =SUMIF(Заказ!$B$5:$B$24,A35,Заказ!$V$5:$V$24) -> 28475.371 | D35: =SUMIF(Заказ!$B$5:$B$24,A35,Заказ!$K$5:$K$24) -> 4645
A36: Шпингалеты | B36: =SUMIF(Заказ!$B$5:$B$24,A36,Заказ!$I$5:$I$24) -> 2745 | C36: =SUMIF(Заказ!$B$5:$B$24,A36,Заказ!$V$5:$V$24) -> 3894.2188 | D36: =SUMIF(Заказ!$B$5:$B$24,A36,Заказ!$K$5:$K$24) -> 436
A37: Аксессуары | B37: =SUMIF(Заказ!$B$5:$B$24,A37,Заказ!$I$5:$I$24) -> 8900 | C37: =SUMIF(Заказ!$B$5:$B$24,A37,Заказ!$V$5:$V$24) -> 12901.47 | D37: =SUMIF(Заказ!$B$5:$B$24,A37,Заказ!$K$5:$K$24) -> 1900

Sheet Параметры
A1: Параметры расчёта импорта дверной фурнитуры (Китай → Бишкек)
A2: Жёлтые ячейки с синим шрифтом — вводные, их можно менять; все листы пересчитаются.
A4: Параметр | B4: Значение | C4: Комментарий / источник
A5: Курс USD → KGS (сом) | B5: 87.5 | C5: Ориентир; подставьте курс НБКР на дату оплаты
A6: Стоимость фуры Китай → Бишкек, $ | B6: 9000 | C6: Со слов заказчика
A7: Грузоподъёмность фуры, кг | B7: 20000 | C7: Типично 20–22 т для тента 13,6 м; фурнитура тяжёлая — упрёмся в вес, а не в объём
A8: Полезный объём фуры, м³ | B8: 86 | C8: Тент 13,6×2,45×2,6 м
A9: Доля фрахта до границы ЕАЭС (входит в там. стоимость) | B9: 0.8 | C9: Таможенная стоимость = цена + доставка до места ввоза (Иркештам/Торугарт). Основной путь — по Китаю, поэтому ~80%
A10: Страхование груза, % от FOB | B10: 0.003 | C10: Ориентир 0,2–0,5%
A11: Таможенный сбор за оформление, % от там. стоимости | B11: 0.004 | C11: 0,40% — разъяснение ГТС КР (economist.kg, 03.04.2025)
A12: НДС при импорте, % | B12: 0.12 | C12: Ставка НДС КР 12%
A13: Включать НДС в себестоимость? (1 = да, 0 = нет) | B13: 1 | C13: Если вы плательщик НДС и берёте его в зачёт — поставьте 0
A14: Таможенный брокер, декларация, $ | B14: 500 | C14: Ориентир за 1 ДТ с 20 позициями
A15: СВХ, разгрузка, доставка до склада, $ | B15: 400 | C15: Ориентир
A16: Комиссия банка / платёжного агента, % от FOB | B16: 0.01 | C16: Перевод в Китай; 0,5–2%
... A20: Оптовая наценка, % | B20: 0.35 | C20: Для оценки выручки; поменяйте под ваш рынок

Sheet Заказ
A1: Заказ на одну фуру и себестоимость по позициям, USD
A2: Синие — вводные (кол-во, цена FOB, вес, объём, ставка пошлины). Цены — ориентир по made-in-china / Global Sources, уточните у фабрик. Логистика распределена пропорционально весу.
A4: № | B4: Категория | C4: Наименование / спецификация | D4: Код ТН ВЭД | E4: Пошлина | F4: Ед. | G4: Кол-во | H4: Цена FOB, $ | I4: Сумма FOB, $ | J4: Вес ед. брутто, кг | K4: Вес итого, кг | L4: Объём ед., м³ | M4: Объём итого, м³ | N4: Логистика, $ | O4: Страховка, $ | P4: Там. стоимость, $ | Q4: Пошлина, $ | R4: Там. сбор, $ | S4: НДС импорт, $ | T4: Прочие расходы, $ | U4: Резерв, $ | V4: Себестоимость итого, $ | W4: Себест. ед., $ | X4: Себест. ед., сом | Y4: Опт. цена ед., сом | Z4: Себест. / FOB
A5: 1 | B5: Ручки | C5: Ручка на розетке, цинк (ЦАМ), хром/никель, эконом | D5: 8302 41 100 0 | E5: 0.1 | F5: компл | G5: 5300 | H5: 2.8 | I5: =G5*H5 -> 14840 | J5: 0.4 | K5: =G5*J5 -> 2120 | L5: 0.0018 | M5: =G5*L5 -> 9.54 | N5: =IF($K$25=0,0,K5/$K$25*Параметры!$B$6) -> 980.37201 | O5: =I5*Параметры!$B$10 -> 44.52 | P5: =I5+N5*Параметры!$B$9+O5 -> 15668.818 | Q5: =P5*E5 -> 1566.8818 | R5: =P5*Параметры!$B$11 -> 62.67527 | S5: =(P5+Q5)*Параметры!$B$12 -> 2068.2839 | T5: =IF($I$25=0,0,I5/$I$25*(Параметры!$B$14+Параметры!$B$15+Параметры!$B$18))+I5*(Параметры!$B$16+Параметры!$B$17) -> 746.62913 | U5: =(I5+N5+O5+Q5+R5+S5*Параметры!$B$13+T5)*Параметры!$B$19 -> 609.28086 | V5: =I5+N5+O5+Q5+R5+S5*Параметры!$B$13+T5+U5 -> 20918.643 | W5: =IF(G5=0,0,V5/G5) -> 3.9469138 | X5: =W5*Параметры!$B$5 -> 345.35495 | Y5: =X5*(1+Параметры!$B$20) -> 466.22919 | Z5: =IF(H5=0,0,W5/H5) -> 1.4096121
A6: 2 | B6: Ручки | C6: Ручка на розетке, цинк, матовый чёрный / PVD-золото, премиум | D6: 8302 41 100 0 | E6: 0.1 | F6: компл | G6: 2600 | H6: 5.5 | I6: =G6*H6 -> 14300 | J6: 0.55 | K6: =G6*J6 -> 1430 | L6: 0.0024 | M6: =G6*L6 -> 6.24 | N6: =IF($K$25=0,0,K6/$K$25*Параметры!$B$6) -> 661.28867 | O6: =I6*Параметры!$B$10 -> 42.9 | P6: =I6+N6*Параметры!$B$9+O6 -> 14871.931 | Q6: =P6*E6 -> 1487.1931 | R6: =P6*Параметры!$B$11 -> 59.487724 | S6: =(P6+Q6)*Параметры!$B$12 -> 1963.0949 | T6: =IF($I$25=0,0,I6/$I$25*(Параметры!$B$14+Параметры!$B$15+Параметры!$B$18))+I6*(Параметры!$B$16+Параметры!$B$17) -> 719.46069 | U6: =(I6+N6+O6+Q6+R6+S6*Параметры!$B$13+T6)*Параметры!$B$19 -> 577.00275 | V6: =I6+N6+O6+Q6+R6+S6*Параметры!$B$13+T6+U6 -> 19810.428 | W6: =IF(G6=0,0,V6/G6) -> 7.6193953 | X6: =W6*Параметры!$B$5 -> 666.69709 | Y6: =X6*(1+Параметры!$B$20) -> 900.04107 | Z6: =IF(H6=0,0,W6/H6) -> 1.3853446
A7: 3 | B7: Ручки | C7: Ручка на планке 85 мм под цилиндр, алюминий/цинк | D7: 8302 41 100 0 | E7: 0.1 | F7: компл | G7: 1300 | H7: 4.5 | I7: =G7*H7 -> 5850 | J7: 0.8 | K7: =G7*J7 -> 1040 | L7: 0.003 | M7: =G7*L7 -> 3.9 | N7: =IF($K$25=0,0,K7/$K$25*Параметры!$B$6) -> 480.93721 | O7: =I7*Параметры!$B$10 -> 17.55 | P7: =I7+N7*Параметры!$B$9+O7 -> 6252.2998 | Q7: =P7*E7 -> 625.22998 | R7: =P7*Параметры!$B$11 -> 25.009199 | S7: =(P7+Q7)*Параметры!$B$12 -> 825.30357 | T7: =IF($I$25=0,0,I7/$I$25*(Параметры!$B$14+Параметры!$B$15+Параметры!$B$18))+I7*(Параметры!$B$16+Параметры!$B$17) -> 294.32483 | U7: =(I7+N7+O7+Q7+R7+S7*Параметры!$B$13+T7)*Параметры!$B$19 -> 243.55064 | V7: =I7+N7+O7+Q7+R7+S7*Параметры!$B$13+T7+U7 -> 8361.9054 | W7: =IF(G7=0,0,V7/G7) -> 6.4322349 | X7: =W7*Параметры!$B$5 -> 562.82056 | Y7: =X7*(1+Параметры!$B$20) -> 759.80775 | Z7: =IF(H7=0,0,W7/H7) -> 1.4293855
A8: 4 | B8: Ручки | C8: Ручка-купе / скоба для раздвижных дверей | D8: 8302 41 100 0 | E8: 0.1 | F8: шт | G8: 1800 | H8: 1.8 | I8: =G8*H8 -> 3240 | J8: 0.15 | K8: =G8*J8 -> 270 | L8: 0.0006 | M8: =G8*L8 -> 1.08 | N8: =IF($K$25=0,0,K8/$K$25*Параметры!$B$6) -> 124.8587 | O8: =I8*Параметры!$B$10 -> 9.72 | P8: =I8+N8*Параметры!$B$9+O8 -> 3349.607 | Q8: =P8*E8 -> 334.9607 | R8: =P8*Параметры!$B$11 -> 13.398428 | S8: =(P8+Q8)*Параметры!$B$12 -> 442.14812 | T8: =IF($I$25=0,0,I8/$I$25*(Параметры!$B$14+Параметры!$B$15+Параметры!$B$18))+I8*(Параметры!$B$16+Параметры!$B$17) -> 163.01067 | U8: =(I8+N8+O8+Q8+R8+S8*Параметры!$B$13+T8)*Параметры!$B$19 -> 129.8429 | V8: =I8+N8+O8+Q8+R8+S8*Параметры!$B$13+T8+U8 -> 4457.9395 | W8: =IF(G8=0,0,V8/G8) -> 2.4766331 | X8: =W8*Параметры!$B$5 -> 216.70539 | Y8: =X8*(1+Параметры!$B$20) -> 292.55228 | Z8: =IF(H8=0,0,W8/H8) -> 1.3759073
A9: 5 | B9: Механизмы | C9: Защёлка межкомнатная механическая (пластиковый язычок) | D9: 8302 41 100 0 | E9: 0.1 | F9: шт | G9: 6600 | H9: 1.6 | I9: =G9*H9 -> 10560 | J9: 0.25 | K9: =G9*J9 -> 1650 | L9: 0.0008 | M9: =G9*L9 -> 5.28 | N9: =IF($K$25=0,0,K9/$K$25*Параметры!$B$6) -> 763.02538 | O9: =I9*Параметры!$B$10 -> 31.68 | P9: =I9+N9*Параметры!$B$9+O9 -> 11202.1 | Q9: =P9*E9 -> 1120.21 | R9: =P9*Параметры!$B$11 -> 44.808401 | S9: =(P9+Q9)*Параметры!$B$12 -> 1478.6772 | T9: =IF($I$25=0,0,I9/$I$25*(Параметры!$B$14+Параметры!$B$15+Параметры!$B$18))+I9*(Параметры!$B$16+Параметры!$B$17) -> 531.29404 | U9: =(I9+N9+O9+Q9+R9+S9*Параметры!$B$13+T9)*Параметры!$B$19 -> 435.89085 | V9: =I9+N9+O9+Q9+R9+S9*Параметры!$B$13+T9+U9 -> 14965.586 | W9: =IF(G9=0,0,V9/G9) -> 2.267513 | X9: =W9*Параметры!$B$5 -> 198.40739 | Y9: =X9*(1+Параметры!$B$20) -> 267.84998 | Z9: =IF(H9=0,0,W9/H9) -> 1.4171956
A10: 6 | B10: Механизмы | C10: Защёлка магнитная бесшумная | D10: 8302 41 100 0 | E10: 0.1 | F10: шт | G10: 3500 | H10: 3.2 | I10: =G10*H10 -> 11200 | J10: 0.3 | K10: =G10*J10 -> 1050 | L10: 0.0009 | M10: =G10*L10 -> 3.15 | N10: =IF($K$25=0,0,K10/$K$25*Параметры!$B$6) -> 485.56161 | O10: =I10*Параметры!$B$10 -> 33.6 | P10: =I10+N10*Параметры!$B$9+O10 -> 11622.049 | Q10: =P10*E10 -> 1162.2049 | R10: =P10*Параметры!$B$11 -> 46.488197 | S10: =(P10+Q10)*Параметры!$B$12 -> 1534.1105 | T10: =IF($I$25=0,0,I10/$I$25*(Параметры!$B$14+Параметры!$B$15+Параметры!$B$18))+I10*(Параметры!$B$16+Параметры!$B$17) -> 563.49368 | U10: =(I10+N10+O10+Q10+R10+S10*Параметры!$B$13+T10)*Параметры!$B$19 -> 450.76377 | V10: =I10+N10+O10+Q10+R10+S10*Параметры!$B$13+T10+U10 -> 15476.223 | W10: =IF(G10=0,0,V10/G10) -> 4.4217779 | X10: =W10*Параметры!$B$5 -> 386.90557 | Y10: =X10*(1+Параметры!$B$20) -> 522.32252 | Z10: =IF(H10=0,0,W10/H10) -> 1.3818056
A11: 7 | B11: Замки | C11: Замок врезной межкомнатный под цилиндр, 85 мм | D11: 8301 40 110 0 | E11: 0.12 | F11: шт | G11: 3500 | H11: 3.8 | I11: =G11*H11 -> 13300 | J11: 0.55 | K11: =G11*J11 -> 1925 | L11: 0.0012 | M11: =G11*L11 -> 4.2 | N11: =IF($K$25=0,0,K11/$K$25*Параметры!$B$6) -> 890.19628 | O11: =I11*Параметры!$B$10 -> 39.9 | P11: =I11+N11*Параметры!$B$9+O11 -> 14052.057 | Q11: =P11*E11 -> 1686.2468 | R11: =P11*Параметры!$B$11 -> 56.208228 | S11: =(P11+Q11)*Параметры!$B$12 -> 1888.5965 | T11: =IF($I$25=0,0,I11/$I$25*(Параметры!$B$14+Параметры!$B$15+Параметры!$B$18))+I11*(Параметры!$B$16+Параметры!$B$17) -> 669.14875 | U11: =(I11+N11+O11+Q11+R11+S11*Параметры!$B$13+T11)*Параметры!$B$19 -> 555.9089 | V11: =I11+N11+O11+Q11+R11+S11*Параметры!$B$13+T11+U11 -> 19086.205 | W11: =IF(G11=0,0,V11/G11) -> 5.4532016 | X11: =W11*Параметры!$B$5 -> 477.15514 | Y11: =X11*(1+Параметры!$B$20) -> 644.15943 | Z11: =IF(H11=0,0,W11/H11) -> 1.435053
A12: 8 | B12: Замки | C12: Замок врезной сантехнический (WC), 85 мм | D12: 8301 40 190 0 | E12: 0.12 | F12: шт | G12: 2200 | H12: 2.4 | I12: =G12*H12 -> 5280 | J12: 0.35 | K12: =G12*J12 -> 770 | L12: 0.001 | M12: =G12*L12 -> 2.2 | N12: =IF($K$25=0,0,K12/$K$25*Параметры!$B$6) -> 356.07851 | O12: =I12*Параметры!$B$10 -> 15.84 | P12: =I12+N12*Параметры!$B$9+O12 -> 5580.7028 | Q12: =P12*E12 -> 669.68434 | R12: =P12*Параметры!$B$11 -> 22.322811 | S12: =(P12+Q12)*Параметры!$B$12 -> 750.04646 | T12: =IF($I$25=0,0,I12/$I$25*(Параметры!$B$14+Параметры!$B$15+Параметры!$B$18))+I12*(Параметры!$B$16+Параметры!$B$17) -> 265.64702 | U12: =(I12+N12+O12+Q12+R12+S12*Параметры!$B$13+T12)*Параметры!$B$19 -> 220.78857 | V12: =I12+N12+O12+Q12+R12+S12*Параметры!$B$13+T12+U12 -> 7580.4077 | W12: =IF(G12=0,0,V12/G12) -> 3.4456399 | X12: =W12*Параметры!$B$5 -> 301.49349 | Y12: =X12*(1+Параметры!$B$20) -> 407.01621 | Z12: =IF(H12=0,0,W12/H12) -> 1.4356833
A13: 9 | B13: Замки | C13: Замок для входной двери сувальдный/цилиндровый, комплект | D13: 8301 40 110 0 | E13: 0.12 | F13: компл | G13: 400 | H13: 9 | I13: =G13*H13 -> 3600 | J13: 1.4 | K13: =G13*J13 -> 560 | L13: 0.0035 | M13: =G13*L13 -> 1.4 | N13: =IF($K$25=0,0,K13/$K$25*Параметры!$B$6) -> 258.96619 | O13: =I13*Параметры!$B$10 -> 10.8 | P13: =I13+N13*Параметры!$B$9+O13 -> 3817.973 | Q13: =P13*E13 -> 458.15675 | R13: =P13*Параметры!$B$11 -> 15.271892 | S13: =(P13+Q13)*Параметры!$B$12 -> 513.13556 | T13: =IF($I$25=0,0,I13/$I$25*(Параметры!$B$14+Параметры!$B$15+Параметры!$B$18))+I13*(Параметры!$B$16+Параметры!$B$17) -> 181.12297 | U13: =(I13+N13+O13+Q13+R13+S13*Параметры!$B$13+T13)*Параметры!$B$19 -> 151.1236 | V13: =I13+N13+O13+Q13+R13+S13*Параметры!$B$13+T13+U13 -> 5188.577 | W13: =IF(G13=0,0,V13/G13) -> 12.971442 | X13: =W13*Параметры!$B$5 -> 1135.0012 | Y13: =X13*(1+Параметры!$B$20) -> 1532.2516 | Z13: =IF(H13=0,0,W13/H13) -> 1.4412714
A14: 10 | B14: Цилиндры | C14: Цилиндровый механизм 60 мм ключ/ключ, латунь, 5 ключей | D14: 8301 60 000 9 | E14: 0.15 | F14: шт | G14: 4400 | H14: 2.6 | I14: =G14*H14 -> 11440 | J14: 0.2 | K14: =G14*J14 -> 880 | L14: 0.0005 | M14: =G14*L14 -> 2.2 | N14: =IF($K$25=0,0,K14/$K$25*Параметры!$B$6) -> 406.94687 | O14: =I14*Параметры!$B$10 -> 34.32 | P14: =I14+N14*Параметры!$B$9+O14 -> 11799.877 | Q14: =P14*E14 -> 1769.9816 | R14: =P14*Параметры!$B$11 -> 47.19951 | S14: =(P14+Q14)*Параметры!$B$12 -> 1628.3831 | T14: =IF($I$25=0,0,I14/$I$25*(Параметры!$B$14+Параметры!$B$15+Параметры!$B$18))+I14*(Параметры!$B$16+Параметры!$B$17) -> 575.56855 | U14: =(I14+N14+O14+Q14+R14+S14*Параметры!$B$13+T14)*Параметры!$B$19 -> 477.07199 | V14: =I14+N14+O14+Q14+R14+S14*Параметры!$B$13+T14+U14 -> 16379.472 | W14: =IF(G14=0,0,V14/G14) -> 3.7226072 | X14: =W14*Параметры!$B$5 -> 325.72813 | Y14: =X14*(1+Параметры!$B$20) -> 439.73297 | Z14: =IF(H14=0,0,W14/H14) -> 1.431772
A15: 11 | B15: Цилиндры | C15: Цилиндровый механизм 60 мм ключ/вертушка, латунь | D15: 8301 60 000 9 | E15: 0.15 | F15: шт | G15: 1800 | H15: 3 | I15: =G15*H15 -> 5400 | J15: 0.22 | K15: =G15*J15 -> 396 | L15: 0.0005 | M15: =G15*L15 -> 0.9 | N15: =IF($K$25=0,0,K15/$K$25*Параметры!$B$6) -> 183.12609 | O15: =I15*Параметры!$B$10 -> 16.2 | P15: =I15+N15*Параметры!$B$9+O15 -> 5562.7009 | Q15: =P15*E15 -> 834.40513 | R15: =P15*Параметры!$B$11 -> 22.250803 | S15: =(P15+Q15)*Параметры!$B$12 -> 767.65272 | T15: =IF($I$25=0,0,I15/$I$25*(Параметры!$B$14+Параметры!$B$15+Параметры!$B$18))+I15*(Параметры!$B$16+Параметры!$B$17) -> 271.68445 | U15: =(I15+N15+O15+Q15+R15+S15*Параметры!$B$13+T15)*Параметры!$B$19 -> 224.85958 | V15: =I15+N15+O15+Q15+R15+S15*Параметры!$B$13+T15+U15 -> 7720.1788 | W15: =IF(G15=0,0,V15/G15) -> 4.2889882 | X15: =W15*Параметры!$B$5 -> 375.28647 | Y15: =X15*(1+Параметры!$B$20) -> 506.63673 | Z15: =IF(H15=0,0,W15/H15) -> 1.4296627
A16: 12 | B16: Фиксаторы | C16: Фиксатор WC (поворотник + индикатор), цинк | D16: 8302 41 100 0 | E16: 0.1 | F16: компл | G16: 2600 | H16: 1.4 | I16: =G16*H16 -> 3640 | J16: 0.15 | K16: =G16*J16 -> 390 | L16: 0.0005 | M16: =G16*L16 -> 1.3 | N16: =IF($K$25=0,0,K16/$K$25*Параметры!$B$6) -> 180.35145 | O16: =I16*Параметры!$B$10 -> 10.92 | P16: =I16+N16*Параметры!$B$9+O16 -> 3795.2012 | Q16: =P16*E16 -> 379.52012 | R16: =P16*Параметры!$B$11 -> 15.180805 | S16: =(P16+Q16)*Параметры!$B$12 -> 500.96655 | T16: =IF($I$25=0,0,I16/$I$25*(Параметры!$B$14+Параметры!$B$15+Параметры!$B$18))+I16*(Параметры!$B$16+Параметры!$B$17) -> 183.13545 | U16: =(I16+N16+O16+Q16+R16+S16*Параметры!$B$13+T16)*Параметры!$B$19 -> 147.30223 | V16: =I16+N16+O16+Q16+R16+S16*Параметры!$B$13+T16+U16 -> 5057.3766 | W16: =IF(G16=0,0,V16/G16) -> 1.9451448 | X16: =W16*Параметры!$B$5 -> 170.20017 | Y16: =X16*(1+Параметры!$B$20) -> 229.77024 | Z16: =IF(H16=0,0,W16/H16) -> 1.3893892
... A24: 20 | B24: Аксессуары | C24: Броненакладка на цилиндр | D24: 8302 41 100 0 | E24: 0.1 | F24: шт | G24: 900 | H24: 2.5 | I24: =G24*H24 -> 2250 | J24: 0.4 | K24: =G24*J24 -> 360 | L24: 0.0008 | M24: =G24*L24 -> 0.72 | N24: =IF($K$25=0,0,K24/$K$25*Параметры!$B$6) -> 166.47827 | O24: =I24*Параметры!$B$10 -> 6.75 | P24: =I24+N24*Параметры!$B$9+O24 -> 2389.9326 | Q24: =P24*E24 -> 238.99326 | R24: =P24*Параметры!$B$11 -> 9.5597304 | S24: =(P24+Q24)*Параметры!$B$12 -> 315.4711 | T24: =IF($I$25=0,0,I24/$I$25*(Параметры!$B$14+Параметры!$B$15+Параметры!$B$18))+I24*(Параметры!$B$16+Параметры!$B$17) -> 113.20186 | U24: =(I24+N24+O24+Q24+R24+S24*Параметры!$B$13+T24)*Параметры!$B$19 -> 93.013627 | V24: =I24+N24+O24+Q24+R24+S24*Параметры!$B$13+T24+U24 -> 3193.4678 | W24: =IF(G24=0,0,V24/G24) -> 3.5482976 | X24: =W24*Параметры!$B$5 -> 310.47604 | Y24: =X24*(1+Параметры!$B$20) -> 419.14265 | Z24: =IF(H24=0,0,W24/H24) -> 1.419319
C25: ИТОГО | G25: =SUM(G5:G24) -> 57300 | I25: =SUM(I5:I24) -> 135765 | K25: =SUM(K5:K24) -> 19462 | M25: =SUM(M5:M24) -> 55.11 | N25: =SUM(N5:N24) -> 9000 | O25: =SUM(O5:O24) -> 407.295 | P25: =SUM(P5:P24) -> 143372.3 | Q25: =SUM(Q5:Q24) -> 13349.09 | R25: =SUM(R5:R24) -> 573.48918 | S25: =SUM(S5:S24) -> 18806.566 | T25: =SUM(T5:T24) -> 6830.6 | ... V25: =SUM(V5:V24) -> 190274 | Z25: =IF(I25=0,0,V25/I25) -> 1.4014952
C27: Загрузка фуры по весу | G27: =K25/Параметры!$B$7 -> 0.9731
C28: Загрузка фуры по объёму | G28: =M25/Параметры!$B$8 -> 0.64081395
C29: Проверка | G29: =IF(OR(G27>1,G28>1),"ПЕРЕГРУЗ — уменьшите кол-во","Помещается в одну фуру") -> Помещается в одну фуру

Sheet Источники и допущения
A1: Что | B1: Источник / допущение
A2: Пошлина 8302 41 (ручки, защёлки, фиксаторы, шпингалеты для дверей) — 10% | B2: alta.ru/tnved/code/8302419000 ; tws.by/tws/tnved/code/10389
A3: Пошлина 8301 40 (замки врезные) — 12% | B3: ifcg.ru/kb/tnved/8301401100 ; ifcg.ru/kb/tnved/8301401900
A4: Пошлина 8302 10 (петли) — 0%; 8302 60 000 9 (доводчики) — 10%; 8301 60 000 9 (цилиндры как части замков) — 15% | B4: tws.by/tws/tnved/code/10385 ; /10397 ; /10383
A5: Таможенный сбор 0,40% от там. стоимости | B5: Разъяснение ГТС КР, economist.kg, 03.04.2025
A6: НДС при импорте в КР — 12% | B6: Ставка НДС КР; режим условного начисления изменён пост. №565 от 20.08.2026 (economist.kg)
A7: Ручки на розетке, цинк: $1,8–4 за компл., премиум $5–10 | B7: made-in-china.com (Handle Trends, Door Lock Handle), Global Sources
A8: Корпус врезного замка: от $1,56 (нерж., MOQ 600), 0,65 кг | B8: globalsources.com, Lock body 8545C-3
A9: Петли, цилиндры, защёлки, шпингалеты, доводчики | B9: Типовые FOB-цены фабрик Вэньчжоу/Гуандуна; уточнить по RFQ
A10: Фура $9 000 | B10: Со слов заказчика
A11: Вес и объём ед. — с упаковкой (брутто) | B11: Оценка по типовым экспортным коробкам; уточнить по упаковочным листам фабрик
A12: Сертификация ЕАЭС | B12: В расчёт не включена — уточнить у брокера, нужна ли декларация/сертификат по позициям
